syns/__init__.py
syns/syns.py
syns-1.0.dist-info/LICENSE
syns-1.0.dist-info/METADATA
syns-1.0.dist-info/WHEEL
syns-1.0.dist-info/entry_points.txt
syns-1.0.dist-info/top_level.txt
syns-1.0.dist-info/RECORD
