Metadata-Version: 2.1
Name: syns
Version: 1.0
Summary: Query German synonyms from openthesaurus.de
Home-page: https://github.com/boi4/syns/
Author: Jan Fecht
Author-email: UNKNOWN
License: UNKNOWN
Platform: UNKNOWN
Requires-Dist: requests
